{
  "openapi": "3.0.1",
  "info": {
    "title": "SmartApiary.API",
    "version": "1.0"
  },
  "paths": {
    "/api/alerts": {
      "get": {
        "tags": [
          "Alerts"
        ],
        "parameters": [
          {
            "name": "unreadOnly",
            "in": "query",
            "schema": {
              "type": "boolean",
              "default": false
            }
          }
        ],
        "responses": {
          "200": {
            "description": "OK"
          }
        }
      }
    },
    "/api/alerts/{id}/read": {
      "patch": {
        "tags": [
          "Alerts"
        ],
        "parameters": [
          {
            "name": "id",
            "in": "path",
            "required": true,
            "schema": {
              "type": "string",
              "format": "uuid"
            }
          }
        ],
        "responses": {
          "200": {
            "description": "OK"
          }
        }
      }
    },
    "/api/alerts/read-all": {
      "patch": {
        "tags": [
          "Alerts"
        ],
        "responses": {
          "200": {
            "description": "OK"
          }
        }
      }
    },
    "/api/apiaries": {
      "get": {
        "tags": [
          "Apiaries"
        ],
        "responses": {
          "200": {
            "description": "OK"
          }
        }
      },
      "post": {
        "tags": [
          "Apiaries"
        ],
        "requestBody": {
          "content": {
            "application/json": {
              "schema": {
                "$ref": "#/components/schemas/CreateApiaryRequest"
              }
            },
            "text/json": {
              "schema": {
                "$ref": "#/components/schemas/CreateApiaryRequest"
              }
            },
            "application/*+json": {
              "schema": {
                "$ref": "#/components/schemas/CreateApiaryRequest"
              }
            }
          }
        },
        "responses": {
          "200": {
            "description": "OK"
          }
        }
      }
    },
    "/api/apiaries/{id}": {
      "get": {
        "tags": [
          "Apiaries"
        ],
        "parameters": [
          {
            "name": "id",
            "in": "path",
            "required": true,
            "schema": {
              "type": "string",
              "format": "uuid"
            }
          }
        ],
        "responses": {
          "200": {
            "description": "OK"
          }
        }
      },
      "put": {
        "tags": [
          "Apiaries"
        ],
        "parameters": [
          {
            "name": "id",
            "in": "path",
            "required": true,
            "schema": {
              "type": "string",
              "format": "uuid"
            }
          }
        ],
        "requestBody": {
          "content": {
            "application/json": {
              "schema": {
                "$ref": "#/components/schemas/UpdateApiaryRequest"
              }
            },
            "text/json": {
              "schema": {
                "$ref": "#/components/schemas/UpdateApiaryRequest"
              }
            },
            "application/*+json": {
              "schema": {
                "$ref": "#/components/schemas/UpdateApiaryRequest"
              }
            }
          }
        },
        "responses": {
          "200": {
            "description": "OK"
          }
        }
      },
      "delete": {
        "tags": [
          "Apiaries"
        ],
        "parameters": [
          {
            "name": "id",
            "in": "path",
            "required": true,
            "schema": {
              "type": "string",
              "format": "uuid"
            }
          }
        ],
        "responses": {
          "200": {
            "description": "OK"
          }
        }
      }
    },
    "/api/apiaries/{id}/hives": {
      "get": {
        "tags": [
          "Apiaries"
        ],
        "parameters": [
          {
            "name": "id",
            "in": "path",
            "required": true,
            "schema": {
              "type": "string",
              "format": "uuid"
            }
          }
        ],
        "responses": {
          "200": {
            "description": "OK"
          }
        }
      }
    },
    "/api/apiaries/{id}/image": {
      "post": {
        "tags": [
          "Apiaries"
        ],
        "parameters": [
          {
            "name": "id",
            "in": "path",
            "required": true,
            "schema": {
              "type": "string",
              "format": "uuid"
            }
          }
        ],
        "requestBody": {
          "content": {
            "multipart/form-data": {
              "schema": {
                "type": "object",
                "properties": {
                  "file": {
                    "type": "string",
                    "format": "binary"
                  }
                }
              },
              "encoding": {
                "file": {
                  "style": "form"
                }
              }
            }
          }
        },
        "responses": {
          "200": {
            "description": "OK"
          }
        }
      }
    },
    "/api/auth/login": {
      "post": {
        "tags": [
          "Auth"
        ],
        "requestBody": {
          "content": {
            "application/json": {
              "schema": {
                "$ref": "#/components/schemas/LoginRequest"
              }
            },
            "text/json": {
              "schema": {
                "$ref": "#/components/schemas/LoginRequest"
              }
            },
            "application/*+json": {
              "schema": {
                "$ref": "#/components/schemas/LoginRequest"
              }
            }
          }
        },
        "responses": {
          "200": {
            "description": "OK"
          }
        }
      }
    },
    "/api/auth/activate": {
      "post": {
        "tags": [
          "Auth"
        ],
        "requestBody": {
          "content": {
            "application/json": {
              "schema": {
                "$ref": "#/components/schemas/SetPasswordRequest"
              }
            },
            "text/json": {
              "schema": {
                "$ref": "#/components/schemas/SetPasswordRequest"
              }
            },
            "application/*+json": {
              "schema": {
                "$ref": "#/components/schemas/SetPasswordRequest"
              }
            }
          }
        },
        "responses": {
          "200": {
            "description": "OK"
          }
        }
      }
    },
    "/api/auth/forgot-password": {
      "post": {
        "tags": [
          "Auth"
        ],
        "requestBody": {
          "content": {
            "application/json": {
              "schema": {
                "$ref": "#/components/schemas/ForgotPasswordRequest"
              }
            },
            "text/json": {
              "schema": {
                "$ref": "#/components/schemas/ForgotPasswordRequest"
              }
            },
            "application/*+json": {
              "schema": {
                "$ref": "#/components/schemas/ForgotPasswordRequest"
              }
            }
          }
        },
        "responses": {
          "200": {
            "description": "OK"
          }
        }
      }
    },
    "/api/auth/reset-password": {
      "post": {
        "tags": [
          "Auth"
        ],
        "requestBody": {
          "content": {
            "application/json": {
              "schema": {
                "$ref": "#/components/schemas/SetPasswordRequest"
              }
            },
            "text/json": {
              "schema": {
                "$ref": "#/components/schemas/SetPasswordRequest"
              }
            },
            "application/*+json": {
              "schema": {
                "$ref": "#/components/schemas/SetPasswordRequest"
              }
            }
          }
        },
        "responses": {
          "200": {
            "description": "OK"
          }
        }
      }
    },
    "/api/apiaries/{apiaryId}/hives/{hiveId}/device/register": {
      "post": {
        "tags": [
          "Devices"
        ],
        "parameters": [
          {
            "name": "apiaryId",
            "in": "path",
            "required": true,
            "schema": {
              "type": "string",
              "format": "uuid"
            }
          },
          {
            "name": "hiveId",
            "in": "path",
            "required": true,
            "schema": {
              "type": "string",
              "format": "uuid"
            }
          }
        ],
        "requestBody": {
          "content": {
            "application/json": {
              "schema": {
                "$ref": "#/components/schemas/RegisterDeviceRequest"
              }
            },
            "text/json": {
              "schema": {
                "$ref": "#/components/schemas/RegisterDeviceRequest"
              }
            },
            "application/*+json": {
              "schema": {
                "$ref": "#/components/schemas/RegisterDeviceRequest"
              }
            }
          }
        },
        "responses": {
          "200": {
            "description": "OK"
          }
        }
      }
    },
    "/api/devices/handshake": {
      "post": {
        "tags": [
          "Devices"
        ],
        "requestBody": {
          "content": {
            "application/json": {
              "schema": {
                "$ref": "#/components/schemas/DeviceHandshakeRequest"
              }
            },
            "text/json": {
              "schema": {
                "$ref": "#/components/schemas/DeviceHandshakeRequest"
              }
            },
            "application/*+json": {
              "schema": {
                "$ref": "#/components/schemas/DeviceHandshakeRequest"
              }
            }
          }
        },
        "responses": {
          "200": {
            "description": "OK"
          }
        }
      }
    },
    "/api/apiaries/{apiaryId}/hives/{hiveId}/diary": {
      "get": {
        "tags": [
          "HiveDiary"
        ],
        "parameters": [
          {
            "name": "apiaryId",
            "in": "path",
            "required": true,
            "schema": {
              "type": "string",
              "format": "uuid"
            }
          },
          {
            "name": "hiveId",
            "in": "path",
            "required": true,
            "schema": {
              "type": "string",
              "format": "uuid"
            }
          },
          {
            "name": "page",
            "in": "query",
            "schema": {
              "type": "integer",
              "format": "int32",
              "default": 1
            }
          },
          {
            "name": "pageSize",
            "in": "query",
            "schema": {
              "type": "integer",
              "format": "int32",
              "default": 10
            }
          }
        ],
        "responses": {
          "200": {
            "description": "OK"
          }
        }
      },
      "post": {
        "tags": [
          "HiveDiary"
        ],
        "parameters": [
          {
            "name": "apiaryId",
            "in": "path",
            "required": true,
            "schema": {
              "type": "string",
              "format": "uuid"
            }
          },
          {
            "name": "hiveId",
            "in": "path",
            "required": true,
            "schema": {
              "type": "string",
              "format": "uuid"
            }
          }
        ],
        "requestBody": {
          "content": {
            "application/json": {
              "schema": {
                "$ref": "#/components/schemas/CreateDiaryEntryRequest"
              }
            },
            "text/json": {
              "schema": {
                "$ref": "#/components/schemas/CreateDiaryEntryRequest"
              }
            },
            "application/*+json": {
              "schema": {
                "$ref": "#/components/schemas/CreateDiaryEntryRequest"
              }
            }
          }
        },
        "responses": {
          "200": {
            "description": "OK"
          }
        }
      }
    },
    "/api/apiaries/{apiaryId}/hives/{hiveId}/diary/{id}": {
      "get": {
        "tags": [
          "HiveDiary"
        ],
        "parameters": [
          {
            "name": "apiaryId",
            "in": "path",
            "required": true,
            "schema": {
              "type": "string",
              "format": "uuid"
            }
          },
          {
            "name": "hiveId",
            "in": "path",
            "required": true,
            "schema": {
              "type": "string",
              "format": "uuid"
            }
          },
          {
            "name": "id",
            "in": "path",
            "required": true,
            "schema": {
              "type": "string",
              "format": "uuid"
            }
          }
        ],
        "responses": {
          "200": {
            "description": "OK"
          }
        }
      },
      "put": {
        "tags": [
          "HiveDiary"
        ],
        "parameters": [
          {
            "name": "apiaryId",
            "in": "path",
            "required": true,
            "schema": {
              "type": "string",
              "format": "uuid"
            }
          },
          {
            "name": "hiveId",
            "in": "path",
            "required": true,
            "schema": {
              "type": "string",
              "format": "uuid"
            }
          },
          {
            "name": "id",
            "in": "path",
            "required": true,
            "schema": {
              "type": "string",
              "format": "uuid"
            }
          }
        ],
        "requestBody": {
          "content": {
            "application/json": {
              "schema": {
                "$ref": "#/components/schemas/CreateDiaryEntryRequest"
              }
            },
            "text/json": {
              "schema": {
                "$ref": "#/components/schemas/CreateDiaryEntryRequest"
              }
            },
            "application/*+json": {
              "schema": {
                "$ref": "#/components/schemas/CreateDiaryEntryRequest"
              }
            }
          }
        },
        "responses": {
          "200": {
            "description": "OK"
          }
        }
      },
      "delete": {
        "tags": [
          "HiveDiary"
        ],
        "parameters": [
          {
            "name": "apiaryId",
            "in": "path",
            "required": true,
            "schema": {
              "type": "string",
              "format": "uuid"
            }
          },
          {
            "name": "hiveId",
            "in": "path",
            "required": true,
            "schema": {
              "type": "string",
              "format": "uuid"
            }
          },
          {
            "name": "id",
            "in": "path",
            "required": true,
            "schema": {
              "type": "string",
              "format": "uuid"
            }
          }
        ],
        "responses": {
          "200": {
            "description": "OK"
          }
        }
      }
    },
    "/api/apiaries/{apiaryId}/hives": {
      "post": {
        "tags": [
          "Hives"
        ],
        "parameters": [
          {
            "name": "apiaryId",
            "in": "path",
            "required": true,
            "schema": {
              "type": "string",
              "format": "uuid"
            }
          }
        ],
        "requestBody": {
          "content": {
            "application/json": {
              "schema": {
                "$ref": "#/components/schemas/CreateHiveRequest"
              }
            },
            "text/json": {
              "schema": {
                "$ref": "#/components/schemas/CreateHiveRequest"
              }
            },
            "application/*+json": {
              "schema": {
                "$ref": "#/components/schemas/CreateHiveRequest"
              }
            }
          }
        },
        "responses": {
          "200": {
            "description": "OK"
          }
        }
      }
    },
    "/api/apiaries/{apiaryId}/hives/{id}": {
      "get": {
        "tags": [
          "Hives"
        ],
        "parameters": [
          {
            "name": "apiaryId",
            "in": "path",
            "required": true,
            "schema": {
              "type": "string",
              "format": "uuid"
            }
          },
          {
            "name": "id",
            "in": "path",
            "required": true,
            "schema": {
              "type": "string",
              "format": "uuid"
            }
          }
        ],
        "responses": {
          "200": {
            "description": "OK"
          }
        }
      },
      "put": {
        "tags": [
          "Hives"
        ],
        "parameters": [
          {
            "name": "apiaryId",
            "in": "path",
            "required": true,
            "schema": {
              "type": "string",
              "format": "uuid"
            }
          },
          {
            "name": "id",
            "in": "path",
            "required": true,
            "schema": {
              "type": "string",
              "format": "uuid"
            }
          }
        ],
        "requestBody": {
          "content": {
            "application/json": {
              "schema": {
                "$ref": "#/components/schemas/UpdateHiveRequest"
              }
            },
            "text/json": {
              "schema": {
                "$ref": "#/components/schemas/UpdateHiveRequest"
              }
            },
            "application/*+json": {
              "schema": {
                "$ref": "#/components/schemas/UpdateHiveRequest"
              }
            }
          }
        },
        "responses": {
          "200": {
            "description": "OK"
          }
        }
      },
      "delete": {
        "tags": [
          "Hives"
        ],
        "parameters": [
          {
            "name": "apiaryId",
            "in": "path",
            "required": true,
            "schema": {
              "type": "string",
              "format": "uuid"
            }
          },
          {
            "name": "id",
            "in": "path",
            "required": true,
            "schema": {
              "type": "string",
              "format": "uuid"
            }
          }
        ],
        "responses": {
          "200": {
            "description": "OK"
          }
        }
      }
    },
    "/api/parcels": {
      "get": {
        "tags": [
          "Parcels"
        ],
        "responses": {
          "200": {
            "description": "OK"
          }
        }
      },
      "post": {
        "tags": [
          "Parcels"
        ],
        "requestBody": {
          "content": {
            "application/json": {
              "schema": {
                "$ref": "#/components/schemas/CreateParcelRequest"
              }
            },
            "text/json": {
              "schema": {
                "$ref": "#/components/schemas/CreateParcelRequest"
              }
            },
            "application/*+json": {
              "schema": {
                "$ref": "#/components/schemas/CreateParcelRequest"
              }
            }
          }
        },
        "responses": {
          "200": {
            "description": "OK"
          }
        }
      }
    },
    "/api/parcels/{id}": {
      "get": {
        "tags": [
          "Parcels"
        ],
        "parameters": [
          {
            "name": "id",
            "in": "path",
            "required": true,
            "schema": {
              "type": "string",
              "format": "uuid"
            }
          }
        ],
        "responses": {
          "200": {
            "description": "OK"
          }
        }
      },
      "put": {
        "tags": [
          "Parcels"
        ],
        "parameters": [
          {
            "name": "id",
            "in": "path",
            "required": true,
            "schema": {
              "type": "string",
              "format": "uuid"
            }
          }
        ],
        "requestBody": {
          "content": {
            "application/json": {
              "schema": {
                "$ref": "#/components/schemas/UpdateParcelRequest"
              }
            },
            "text/json": {
              "schema": {
                "$ref": "#/components/schemas/UpdateParcelRequest"
              }
            },
            "application/*+json": {
              "schema": {
                "$ref": "#/components/schemas/UpdateParcelRequest"
              }
            }
          }
        },
        "responses": {
          "200": {
            "description": "OK"
          }
        }
      }
    },
    "/api/parcels/{id}/crop": {
      "put": {
        "tags": [
          "Parcels"
        ],
        "parameters": [
          {
            "name": "id",
            "in": "path",
            "required": true,
            "schema": {
              "type": "string",
              "format": "uuid"
            }
          }
        ],
        "requestBody": {
          "content": {
            "application/json": {
              "schema": {
                "$ref": "#/components/schemas/SetCropRequest"
              }
            },
            "text/json": {
              "schema": {
                "$ref": "#/components/schemas/SetCropRequest"
              }
            },
            "application/*+json": {
              "schema": {
                "$ref": "#/components/schemas/SetCropRequest"
              }
            }
          }
        },
        "responses": {
          "200": {
            "description": "OK"
          }
        }
      },
      "delete": {
        "tags": [
          "Parcels"
        ],
        "parameters": [
          {
            "name": "id",
            "in": "path",
            "required": true,
            "schema": {
              "type": "string",
              "format": "uuid"
            }
          }
        ],
        "responses": {
          "200": {
            "description": "OK"
          }
        }
      }
    },
    "/api/parcels/public": {
      "get": {
        "tags": [
          "Parcels"
        ],
        "responses": {
          "200": {
            "description": "OK"
          }
        }
      }
    },
    "/api/parcels/nearby": {
      "get": {
        "tags": [
          "Parcels"
        ],
        "parameters": [
          {
            "name": "apiaryId",
            "in": "query",
            "schema": {
              "type": "string",
              "format": "uuid"
            }
          },
          {
            "name": "radiusKm",
            "in": "query",
            "schema": {
              "type": "number",
              "format": "double",
              "default": 5
            }
          }
        ],
        "responses": {
          "200": {
            "description": "OK"
          }
        }
      }
    },
    "/api/users/me/settings": {
      "get": {
        "tags": [
          "Profile"
        ],
        "responses": {
          "200": {
            "description": "OK"
          }
        }
      },
      "put": {
        "tags": [
          "Profile"
        ],
        "requestBody": {
          "content": {
            "application/json": {
              "schema": {
                "$ref": "#/components/schemas/UpdateUserSettingsRequest"
              }
            },
            "text/json": {
              "schema": {
                "$ref": "#/components/schemas/UpdateUserSettingsRequest"
              }
            },
            "application/*+json": {
              "schema": {
                "$ref": "#/components/schemas/UpdateUserSettingsRequest"
              }
            }
          }
        },
        "responses": {
          "200": {
            "description": "OK"
          }
        }
      }
    },
    "/api/spraying": {
      "get": {
        "tags": [
          "Spraying"
        ],
        "responses": {
          "200": {
            "description": "OK"
          }
        }
      },
      "post": {
        "tags": [
          "Spraying"
        ],
        "requestBody": {
          "content": {
            "application/json": {
              "schema": {
                "$ref": "#/components/schemas/CreateSprayingRequest"
              }
            },
            "text/json": {
              "schema": {
                "$ref": "#/components/schemas/CreateSprayingRequest"
              }
            },
            "application/*+json": {
              "schema": {
                "$ref": "#/components/schemas/CreateSprayingRequest"
              }
            }
          }
        },
        "responses": {
          "200": {
            "description": "OK"
          }
        }
      }
    },
    "/api/spraying/{id}": {
      "get": {
        "tags": [
          "Spraying"
        ],
        "parameters": [
          {
            "name": "id",
            "in": "path",
            "required": true,
            "schema": {
              "type": "string",
              "format": "uuid"
            }
          }
        ],
        "responses": {
          "200": {
            "description": "OK"
          }
        }
      },
      "put": {
        "tags": [
          "Spraying"
        ],
        "parameters": [
          {
            "name": "id",
            "in": "path",
            "required": true,
            "schema": {
              "type": "string",
              "format": "uuid"
            }
          }
        ],
        "requestBody": {
          "content": {
            "application/json": {
              "schema": {
                "$ref": "#/components/schemas/UpdateSprayingRequest"
              }
            },
            "text/json": {
              "schema": {
                "$ref": "#/components/schemas/UpdateSprayingRequest"
              }
            },
            "application/*+json": {
              "schema": {
                "$ref": "#/components/schemas/UpdateSprayingRequest"
              }
            }
          }
        },
        "responses": {
          "200": {
            "description": "OK"
          }
        }
      },
      "delete": {
        "tags": [
          "Spraying"
        ],
        "parameters": [
          {
            "name": "id",
            "in": "path",
            "required": true,
            "schema": {
              "type": "string",
              "format": "uuid"
            }
          }
        ],
        "responses": {
          "200": {
            "description": "OK"
          }
        }
      }
    },
    "/api/spraying/{id}/notification-status": {
      "get": {
        "tags": [
          "Spraying"
        ],
        "parameters": [
          {
            "name": "id",
            "in": "path",
            "required": true,
            "schema": {
              "type": "string",
              "format": "uuid"
            }
          }
        ],
        "responses": {
          "200": {
            "description": "OK"
          }
        }
      }
    },
    "/api/spraying/logs": {
      "get": {
        "tags": [
          "Spraying"
        ],
        "parameters": [
          {
            "name": "parcelId",
            "in": "query",
            "schema": {
              "type": "string",
              "format": "uuid"
            }
          },
          {
            "name": "from",
            "in": "query",
            "schema": {
              "type": "string",
              "format": "date-time"
            }
          },
          {
            "name": "to",
            "in": "query",
            "schema": {
              "type": "string",
              "format": "date-time"
            }
          }
        ],
        "responses": {
          "200": {
            "description": "OK"
          }
        }
      }
    },
    "/api/spraying/logs/export": {
      "get": {
        "tags": [
          "Spraying"
        ],
        "parameters": [
          {
            "name": "parcelId",
            "in": "query",
            "schema": {
              "type": "string",
              "format": "uuid"
            }
          },
          {
            "name": "from",
            "in": "query",
            "schema": {
              "type": "string",
              "format": "date-time"
            }
          },
          {
            "name": "to",
            "in": "query",
            "schema": {
              "type": "string",
              "format": "date-time"
            }
          }
        ],
        "responses": {
          "200": {
            "description": "OK"
          }
        }
      }
    },
    "/api/telemetry/ingest": {
      "post": {
        "tags": [
          "Telemetry"
        ],
        "parameters": [
          {
            "name": "X-Device-Token",
            "in": "header",
            "schema": {
              "type": "string"
            }
          }
        ],
        "requestBody": {
          "content": {
            "application/json": {
              "schema": {
                "$ref": "#/components/schemas/TelemetryRequest"
              }
            },
            "text/json": {
              "schema": {
                "$ref": "#/components/schemas/TelemetryRequest"
              }
            },
            "application/*+json": {
              "schema": {
                "$ref": "#/components/schemas/TelemetryRequest"
              }
            }
          }
        },
        "responses": {
          "200": {
            "description": "OK"
          }
        }
      }
    },
    "/api/telemetry/apiaries/{apiaryId}": {
      "get": {
        "tags": [
          "Telemetry"
        ],
        "parameters": [
          {
            "name": "apiaryId",
            "in": "path",
            "required": true,
            "schema": {
              "type": "string",
              "format": "uuid"
            }
          },
          {
            "name": "days",
            "in": "query",
            "schema": {
              "type": "integer",
              "format": "int32",
              "default": 7
            }
          }
        ],
        "responses": {
          "200": {
            "description": "OK"
          }
        }
      }
    },
    "/api/users": {
      "get": {
        "tags": [
          "Users"
        ],
        "responses": {
          "200": {
            "description": "OK"
          }
        }
      },
      "post": {
        "tags": [
          "Users"
        ],
        "requestBody": {
          "content": {
            "application/json": {
              "schema": {
                "$ref": "#/components/schemas/CreateUserRequest"
              }
            },
            "text/json": {
              "schema": {
                "$ref": "#/components/schemas/CreateUserRequest"
              }
            },
            "application/*+json": {
              "schema": {
                "$ref": "#/components/schemas/CreateUserRequest"
              }
            }
          }
        },
        "responses": {
          "200": {
            "description": "OK"
          }
        }
      }
    },
    "/api/users/{id}": {
      "get": {
        "tags": [
          "Users"
        ],
        "parameters": [
          {
            "name": "id",
            "in": "path",
            "required": true,
            "schema": {
              "type": "string",
              "format": "uuid"
            }
          }
        ],
        "responses": {
          "200": {
            "description": "OK"
          }
        }
      },
      "delete": {
        "tags": [
          "Users"
        ],
        "parameters": [
          {
            "name": "id",
            "in": "path",
            "required": true,
            "schema": {
              "type": "string",
              "format": "uuid"
            }
          }
        ],
        "responses": {
          "200": {
            "description": "OK"
          }
        }
      }
    },
    "/api/users/{id}/suspend": {
      "patch": {
        "tags": [
          "Users"
        ],
        "parameters": [
          {
            "name": "id",
            "in": "path",
            "required": true,
            "schema": {
              "type": "string",
              "format": "uuid"
            }
          }
        ],
        "responses": {
          "200": {
            "description": "OK"
          }
        }
      }
    },
    "/api/users/{id}/set-password": {
      "patch": {
        "tags": [
          "Users"
        ],
        "parameters": [
          {
            "name": "id",
            "in": "path",
            "required": true,
            "schema": {
              "type": "string",
              "format": "uuid"
            }
          }
        ],
        "requestBody": {
          "content": {
            "application/json": {
              "schema": {
                "$ref": "#/components/schemas/SetPasswordRequest"
              }
            },
            "text/json": {
              "schema": {
                "$ref": "#/components/schemas/SetPasswordRequest"
              }
            },
            "application/*+json": {
              "schema": {
                "$ref": "#/components/schemas/SetPasswordRequest"
              }
            }
          }
        },
        "responses": {
          "200": {
            "description": "OK"
          }
        }
      }
    }
  },
  "components": {
    "schemas": {
      "CreateApiaryRequest": {
        "type": "object",
        "properties": {
          "name": {
            "type": "string",
            "nullable": true
          },
          "latitude": {
            "type": "number",
            "format": "double"
          },
          "longitude": {
            "type": "number",
            "format": "double"
          },
          "description": {
            "type": "string",
            "nullable": true
          }
        },
        "additionalProperties": false
      },
      "CreateDiaryEntryRequest": {
        "type": "object",
        "properties": {
          "inspectionDate": {
            "type": "string",
            "format": "date-time"
          },
          "floorColor": {
            "type": "string",
            "nullable": true
          },
          "honeyFrames": {
            "type": "integer",
            "format": "int32"
          },
          "honeyAmount": {
            "type": "number",
            "format": "double"
          },
          "broodFrames": {
            "type": "integer",
            "format": "int32"
          },
          "queenPresent": {
            "type": "boolean"
          },
          "notes": {
            "type": "string",
            "nullable": true
          }
        },
        "additionalProperties": false
      },
      "CreateHiveRequest": {
        "type": "object",
        "properties": {
          "label": {
            "type": "string",
            "nullable": true
          },
          "hiveType": {
            "type": "string",
            "nullable": true
          },
          "frameColor": {
            "type": "string",
            "nullable": true
          },
          "queenAge": {
            "type": "integer",
            "format": "int32"
          },
          "notes": {
            "type": "string",
            "nullable": true
          }
        },
        "additionalProperties": false
      },
      "CreateParcelRequest": {
        "type": "object",
        "properties": {
          "name": {
            "type": "string",
            "nullable": true
          },
          "latitude": {
            "type": "number",
            "format": "double"
          },
          "longitude": {
            "type": "number",
            "format": "double"
          },
          "areaHectares": {
            "type": "number",
            "format": "double",
            "nullable": true
          }
        },
        "additionalProperties": false
      },
      "CreateSprayingRequest": {
        "type": "object",
        "properties": {
          "parcelId": {
            "type": "string",
            "format": "uuid"
          },
          "plannedStartTime": {
            "type": "string",
            "format": "date-time"
          },
          "durationHours": {
            "type": "integer",
            "format": "int32"
          },
          "substanceType": {
            "type": "string",
            "nullable": true
          }
        },
        "additionalProperties": false
      },
      "CreateUserRequest": {
        "type": "object",
        "properties": {
          "firstName": {
            "type": "string",
            "nullable": true
          },
          "lastName": {
            "type": "string",
            "nullable": true
          },
          "email": {
            "type": "string",
            "nullable": true
          },
          "phone": {
            "type": "string",
            "nullable": true
          },
          "role": {
            "type": "string",
            "nullable": true
          }
        },
        "additionalProperties": false
      },
      "DeviceHandshakeRequest": {
        "type": "object",
        "properties": {
          "uniqueDeviceId": {
            "type": "string",
            "nullable": true
          },
          "serialNumber": {
            "type": "string",
            "nullable": true
          }
        },
        "additionalProperties": false
      },
      "ForgotPasswordRequest": {
        "type": "object",
        "properties": {
          "email": {
            "type": "string",
            "nullable": true
          }
        },
        "additionalProperties": false
      },
      "LoginRequest": {
        "type": "object",
        "properties": {
          "email": {
            "type": "string",
            "nullable": true
          },
          "password": {
            "type": "string",
            "nullable": true
          }
        },
        "additionalProperties": false
      },
      "RegisterDeviceRequest": {
        "type": "object",
        "properties": {
          "serialNumber": {
            "type": "string",
            "nullable": true
          }
        },
        "additionalProperties": false
      },
      "SetCropRequest": {
        "type": "object",
        "properties": {
          "cropType": {
            "type": "string",
            "nullable": true
          },
          "bloomingPeriod": {
            "type": "string",
            "nullable": true
          },
          "additionalInfo": {
            "type": "string",
            "nullable": true
          }
        },
        "additionalProperties": false
      },
      "SetPasswordRequest": {
        "type": "object",
        "properties": {
          "token": {
            "type": "string",
            "nullable": true
          },
          "password": {
            "type": "string",
            "nullable": true
          },
          "confirmPassword": {
            "type": "string",
            "nullable": true
          }
        },
        "additionalProperties": false
      },
      "TelemetryRequest": {
        "type": "object",
        "properties": {
          "weight": {
            "type": "number",
            "format": "double"
          },
          "humidity": {
            "type": "number",
            "format": "double"
          },
          "internalTemperature": {
            "type": "number",
            "format": "double"
          },
          "batteryLevel": {
            "type": "number",
            "format": "double"
          },
          "recordedAt": {
            "type": "string",
            "format": "date-time"
          }
        },
        "additionalProperties": false
      },
      "UpdateApiaryRequest": {
        "type": "object",
        "properties": {
          "name": {
            "type": "string",
            "nullable": true
          },
          "latitude": {
            "type": "number",
            "format": "double"
          },
          "longitude": {
            "type": "number",
            "format": "double"
          },
          "description": {
            "type": "string",
            "nullable": true
          }
        },
        "additionalProperties": false
      },
      "UpdateHiveRequest": {
        "type": "object",
        "properties": {
          "label": {
            "type": "string",
            "nullable": true
          },
          "hiveType": {
            "type": "string",
            "nullable": true
          },
          "frameColor": {
            "type": "string",
            "nullable": true
          },
          "queenAge": {
            "type": "integer",
            "format": "int32"
          },
          "notes": {
            "type": "string",
            "nullable": true
          }
        },
        "additionalProperties": false
      },
      "UpdateParcelRequest": {
        "type": "object",
        "properties": {
          "name": {
            "type": "string",
            "nullable": true
          },
          "latitude": {
            "type": "number",
            "format": "double"
          },
          "longitude": {
            "type": "number",
            "format": "double"
          },
          "areaHectares": {
            "type": "number",
            "format": "double",
            "nullable": true
          }
        },
        "additionalProperties": false
      },
      "UpdateSprayingRequest": {
        "type": "object",
        "properties": {
          "plannedStartTime": {
            "type": "string",
            "format": "date-time"
          },
          "durationHours": {
            "type": "integer",
            "format": "int32"
          },
          "substanceType": {
            "type": "string",
            "nullable": true
          }
        },
        "additionalProperties": false
      },
      "UpdateUserSettingsRequest": {
        "type": "object",
        "properties": {
          "weightDropThreshold": {
            "type": "number",
            "format": "double"
          }
        },
        "additionalProperties": false
      }
    },
    "securitySchemes": {
      "Bearer": {
        "type": "http",
        "scheme": "bearer",
        "bearerFormat": "JWT"
      }
    }
  },
  "security": [
    {
      "Bearer": [ ]
    }
  ]
}